stcp/__init__.py
stcp/_hash_cache.py
stcp/_primitives.py
stcp/_util.py
stcp/api.py
stcp/util.py
stcp_api-1.1.5.dist-info/LICENSE
stcp_api-1.1.5.dist-info/METADATA
stcp_api-1.1.5.dist-info/WHEEL
stcp_api-1.1.5.dist-info/top_level.txt
stcp_api-1.1.5.dist-info/RECORD
